idownload/__init__.py
idownload/__main__.py
idownload/cli.py
idownload/exceptions.py
idownload/sources/__init__.py
idownload/sources/pinterest.py
idownload-1.2.0.dist-info/LICENSE
idownload-1.2.0.dist-info/METADATA
idownload-1.2.0.dist-info/WHEEL
idownload-1.2.0.dist-info/entry_points.txt
idownload-1.2.0.dist-info/top_level.txt
idownload-1.2.0.dist-info/RECORD
